rusgenderdetection/__init__.py
rusgenderdetection/detectbyrusname.py
rus_gender_detection-1.0.0.dist-info/LICENSE
rus_gender_detection-1.0.0.dist-info/METADATA
rus_gender_detection-1.0.0.dist-info/WHEEL
rus_gender_detection-1.0.0.dist-info/top_level.txt
rus_gender_detection-1.0.0.dist-info/RECORD
