Metadata-Version: 2.1
Name: rus-gender-detection
Version: 1.0.0
Summary: Determinates gender by rusiian full name
Home-page: https://github.com/Omni-K/rus_gender_detection
Author: Nikolay Putko
Author-email: nikolay@putko.ru
License: MIT License
Platform: UNKNOWN
License-File: LICENSE
